ontolutils/__init__.py
ontolutils/_cfg.py
ontolutils/_version.py
ontolutils/cache.py
ontolutils/config.py
ontolutils/typing.py
ontolutils/classes/__init__.py
ontolutils/classes/decorator.py
ontolutils/classes/query_util.py
ontolutils/classes/thing.py
ontolutils/classes/thingmodel.py
ontolutils/classes/urivalue.py
ontolutils/classes/utils.py
ontolutils/ex/__init__.py
ontolutils/ex/dcat/__init__.py
ontolutils/ex/dcat/resource.py
ontolutils/ex/dcat/role.py
ontolutils/ex/foaf/__init__.py
ontolutils/ex/foaf/agent.py
ontolutils/ex/hdf5/__init__.py
ontolutils/ex/hdf5/allotrope.py
ontolutils/ex/m4i/__init__.py
ontolutils/ex/m4i/m4i.py
ontolutils/ex/pimsii/__init__.py
ontolutils/ex/pimsii/property.py
ontolutils/ex/pimsii/variable.py
ontolutils/ex/prov/__init__.py
ontolutils/ex/prov/attribution.py
ontolutils/ex/qudt/__init__.py
ontolutils/ex/qudt/conversion.py
ontolutils/ex/qudt/utils.py
ontolutils/ex/schema/__init__.py
ontolutils/ex/schema/creative_work.py
ontolutils/ex/schema/project.py
ontolutils/ex/schema/thing.py
ontolutils/ex/sis/__init__.py
ontolutils/ex/sis/measurement_uncertainty.py
ontolutils/ex/skos/__init__.py
ontolutils/ex/skos/concept.py
ontolutils/ex/sosa/__init__.py
ontolutils/ex/spdx/__init__.py
ontolutils/ex/spdx/spdx.py
ontolutils/ex/ssn/__init__.py
ontolutils/ex/ssn/ssn.py
ontolutils/namespacelib/__dev.py
ontolutils/namespacelib/__init__.py
ontolutils/namespacelib/_iana_utils.py
ontolutils/namespacelib/codemeta.py
ontolutils/namespacelib/hdf5.py
ontolutils/namespacelib/m4i.py
ontolutils/namespacelib/obo.py
ontolutils/namespacelib/qudt_kind.py
ontolutils/namespacelib/qudt_unit.py
ontolutils/namespacelib/schema.py
ontolutils/namespacelib/spdx.py
ontolutils/namespacelib/ssn_system.py
ontolutils/utils/__init__.py
ontolutils/utils/qudt_units.py
ontolutils-0.27.5.dist-info/licenses/LICENSE
ontolutils-0.27.5.dist-info/METADATA
ontolutils-0.27.5.dist-info/WHEEL
ontolutils-0.27.5.dist-info/top_level.txt
ontolutils-0.27.5.dist-info/RECORD
