Metadata-Version: 2.4
Name: ontolutils
Version: 0.27.5
Summary: Utility library for the work with ontologies.
Author-email: Matthias Probst <matthias.probst@kit.edu>
License-Expression: MIT
Classifier: Programming Language :: Python :: 3.9
Classifier: Programming Language :: Python :: 3.10
Classifier: Programming Language :: Python :: 3.11
Classifier: Programming Language :: Python :: 3.12
Classifier: Programming Language :: Python :: 3.13
Classifier: Programming Language :: Python :: 3.14
Classifier: Operating System :: OS Independent
Classifier: Development Status :: 4 - Beta
Requires-Python: <3.15,>=3.9
License-File: LICENSE
Requires-Dist: rdflib>=7.0.0
Requires-Dist: pydantic[email]>=2.8.2
Requires-Dist: python-dateutil>=2.9.0
Requires-Dist: requests>=2.32.3
Requires-Dist: appdirs>=1.4.4
Requires-Dist: PyYAML>=6.0
Provides-Extra: test
Requires-Dist: pytest>=8.3.2; extra == "test"
Requires-Dist: pytest-cov>=5.0.0; extra == "test"
Requires-Dist: pylint>=3.2.6; extra == "test"
Requires-Dist: pyyaml; extra == "test"
Requires-Dist: pint; extra == "test"
Requires-Dist: xarray; extra == "test"
Requires-Dist: numpy; extra == "test"
Requires-Dist: pyshacl; extra == "test"
Provides-Extra: complete
Requires-Dist: ontolutils[test]; extra == "complete"
Dynamic: license-file
